pyrfc_read/__init__.py
pyrfc_read/pyrfc_read.py
pyrfc_read/utils.py
pyrfc_read-1.0.2.dist-info/LICENSE
pyrfc_read-1.0.2.dist-info/METADATA
pyrfc_read-1.0.2.dist-info/WHEEL
pyrfc_read-1.0.2.dist-info/top_level.txt
pyrfc_read-1.0.2.dist-info/RECORD
