Metadata-Version: 2.1
Name: pyrfc_read
Version: 1.0.2
Summary: Read data from SAP R/3 Systems
Home-page: https://github.com/amarvin/pyrfc-read
Author: Alex Marvin
Author-email: alex.marvin@gmail.com
Classifier: Programming Language :: Python :: 3
Classifier: License :: OSI Approved :: MIT License
Classifier: Operating System :: OS Independent
Requires-Python: >=3.6
License-File: LICENSE
Requires-Dist: pyrfc==3.3.1
Provides-Extra: dev
Requires-Dist: black; extra == "dev"
Requires-Dist: pyproject-flake8; extra == "dev"
Requires-Dist: isort[colors]; extra == "dev"
Provides-Extra: test
Requires-Dist: pytest; extra == "test"
Requires-Dist: pytest-cov; extra == "test"
